setup.py
slackard.py
slackard.egg-info/PKG-INFO
slackard.egg-info/SOURCES.txt
slackard.egg-info/dependency_links.txt
slackard.egg-info/entry_points.txt
slackard.egg-info/requires.txt
slackard.egg-info/top_level.txt