Metadata-Version: 1.1
Name: slackard
Version: 2.0.0
Summary: A pluggable bot for slack.com
Home-page: https://github.com/aelse/slackard
Author: Alexander Else
Author-email: aelse@else.id.au
License: BSD
Platform: UNKNOWN
Classifier: Development Status :: 4 - Beta
Classifier: Intended Audience :: Developers
Classifier: Intended Audience :: System Administrators
Classifier: License :: OSI Approved :: BSD License
Classifier: Programming Language :: Python
Classifier: Programming Language :: Python :: 2.7
Classifier: Programming Language :: Python :: 3.3
Classifier: Programming Language :: Python :: 3.4
Classifier: Topic :: Communications :: Chat
Classifier: Topic :: Office/Business :: Groupware
